{
  "flower_1": {
    "angle_indices": [
      72,
      73,
      74,
      75,
      76
    ],
    "background_dist": 0.0
  },
  "flower_2": {
    "angle_indices": [
      86,
      87,
      88,
      89,
      90,
      91,
      92
    ],
    "background_dist": 0.0
  },
  "flower_3": {
    "angle_indices": [
      101,
      102,
      103,
      104,
      105,
      106,
      107,
      108,
      109,
      110,
      111,
      112
    ],
    "background_dist": 0.244
  },
  "flower_4": {
    "angle_indices": [
      158,
      159,
      160,
      161,
      162,
      163,
      164,
      165,
      166,
      167,
      168,
      169,
      170,
      171,
      172,
      173,
      174,
      175,
      176,
      177
    ],
    "background_dist": 0.19
  },
  "flower_5": {
    "angle_indices": [
      219,
      220,
      221
    ],
    "background_dist": 0.241
  }
}