{
    "event_type": "flower_visit",
    "event_id": "flower_1_20260410195748346796",
    "flower_id": "flower_1",
    "background_dist": 0.19,
    "start_time": 1775869065.5470169,
    "end_time": 1775869068.346755,
    "num_scans": 42,
    "angles": [
        105,
        106,
        107,
        108,
        109,
        110,
        111,
        112,
        113,
        114,
        115,
        116
    ],
    "distance_series": [
        [
            0.269,
            0.19,
            0.178,
            0.173,
            0.154,
            0.152,
            0.162,
            0.177,
            0.184,
            0.19,
            0.189,
            0.194
        ],
        [
            0.262,
            0.188,
            0.18,
            0.171,
            0.156,
            0.152,
            0.163,
            0.177,
            0.176,
            0.185,
            0.188,
            0.196
        ],
        [
            0.259,
            0.186,
            0.182,
            0.174,
            0.157,
            0.15,
            0.165,
            0.178,
            0.175,
            0.18,
            0.189,
            0.196
        ],
        [
            0.262,
            0.189,
            0.18,
            0.173,
            0.162,
            0.151,
            0.165,
            0.173,
            0.178,
            0.189,
            0.192,
            0.195
        ],
        [
            0.259,
            0.189,
            0.183,
            0.178,
            0.167,
            0.151,
            0.164,
            0.177,
            0.181,
            0.185,
            0.195,
            0.202
        ],
        [
            0.225,
            0.19,
            0.187,
            0.176,
            0.17,
            0.156,
            0.163,
            0.178,
            0.189,
            0.191,
            0.199,
            0.205
        ],
        [
            0.263,
            0.184,
            0.179,
            0.177,
            0.167,
            0.157,
            0.162,
            0.179,
            0.192,
            0.189,
            0.198,
            0.198
        ],
        [
            0.302,
            0.184,
            0.185,
            0.181,
            0.16,
            0.156,
            0.166,
            0.178,
            0.196,
            0.186,
            0.196,
            0.2
        ],
        [
            0.302,
            0.186,
            0.181,
            0.184,
            0.158,
            0.156,
            0.164,
            0.171,
            0.196,
            0.188,
            0.191,
            0.199
        ],
        [
            0.305,
            0.185,
            0.183,
            0.184,
            0.156,
            0.158,
            0.16,
            0.173,
            0.189,
            0.192,
            0.194,
            0.202
        ],
        [
            0.269,
            0.189,
            0.181,
            0.184,
            0.161,
            0.154,
            0.158,
            0.17,
            0.191,
            0.192,
            0.195,
            0.2
        ],
        [
            0.231,
            0.189,
            0.18,
            0.182,
            0.168,
            0.148,
            0.155,
            0.169,
            0.187,
            0.192,
            0.197,
            0.199
        ],
        [
            0.197,
            0.188,
            0.179,
            0.178,
            0.166,
            0.151,
            0.158,
            0.172,
            0.184,
            0.191,
            0.199,
            0.2
        ],
        [
            0.196,
            0.192,
            0.176,
            0.181,
            0.169,
            0.148,
            0.158,
            0.174,
            0.19,
            0.192,
            0.193,
            0.199
        ],
        [
            0.195,
            0.192,
            0.182,
            0.184,
            0.165,
            0.149,
            0.158,
            0.174,
            0.186,
            0.193,
            0.195,
            0.2
        ],
        [
            0.193,
            0.195,
            0.181,
            0.182,
            0.163,
            0.151,
            0.16,
            0.176,
            0.185,
            0.188,
            0.194,
            0.202
        ],
        [
            0.194,
            0.189,
            0.18,
            0.177,
            0.162,
            0.148,
            0.156,
            0.171,
            0.185,
            0.188,
            0.197,
            0.198
        ],
        [
            0.229,
            0.189,
            0.179,
            0.18,
            0.155,
            0.148,
            0.156,
            0.173,
            0.185,
            0.185,
            0.193,
            0.195
        ],
        [
            0.268,
            0.185,
            0.176,
            0.178,
            0.156,
            0.147,
            0.156,
            0.171,
            0.185,
            0.186,
            0.193,
            0.202
        ],
        [
            0.303,
            0.188,
            0.176,
            0.181,
            0.158,
            0.146,
            0.154,
            0.17,
            0.187,
            0.187,
            0.198,
            0.201
        ],
        [
            0.309,
            0.189,
            0.175,
            0.178,
            0.165,
            0.151,
            0.158,
            0.164,
            0.186,
            0.192,
            0.191,
            0.198
        ],
        [
            0.273,
            0.193,
            0.181,
            0.181,
            0.172,
            0.152,
            0.151,
            0.167,
            0.187,
            0.19,
            0.189,
            0.201
        ],
        [
            0.237,
            0.194,
            0.18,
            0.185,
            0.175,
            0.152,
            0.148,
            0.163,
            0.185,
            0.192,
            0.191,
            0.202
        ],
        [
            0.242,
            0.194,
            0.181,
            0.182,
            0.175,
            0.156,
            0.151,
            0.165,
            0.185,
            0.193,
            0.191,
            0.201
        ],
        [
            0.237,
            0.194,
            0.179,
            0.179,
            0.177,
            0.155,
            0.15,
            0.165,
            0.186,
            0.188,
            0.195,
            0.204
        ],
        [
            0.235,
            0.19,
            0.183,
            0.187,
            0.177,
            0.157,
            0.151,
            0.165,
            0.179,
            0.195,
            0.201,
            0.202
        ],
        [
            0.234,
            0.192,
            0.183,
            0.188,
            0.167,
            0.16,
            0.152,
            0.167,
            0.181,
            0.192,
            0.196,
            0.203
        ],
        [
            0.192,
            0.189,
            0.187,
            0.185,
            0.165,
            0.156,
            0.151,
            0.168,
            0.186,
            0.194,
            0.198,
            0.198
        ],
        [
            0.23,
            0.19,
            0.187,
            0.184,
            0.164,
            0.155,
            0.15,
            0.165,
            0.182,
            0.199,
            0.198,
            0.199
        ],
        [
            0.229,
            0.187,
            0.181,
            0.185,
            0.164,
            0.151,
            0.152,
            0.17,
            0.187,
            0.197,
            0.195,
            0.2
        ],
        [
            0.228,
            0.193,
            0.184,
            0.181,
            0.172,
            0.15,
            0.151,
            0.166,
            0.181,
            0.197,
            0.193,
            0.195
        ],
        [
            0.267,
            0.189,
            0.183,
            0.177,
            0.174,
            0.15,
            0.154,
            0.168,
            0.179,
            0.195,
            0.187,
            0.193
        ],
        [
            0.222,
            0.186,
            0.181,
            0.175,
            0.17,
            0.154,
            0.154,
            0.171,
            0.177,
            0.191,
            0.183,
            0.193
        ],
        [
            0.221,
            0.184,
            0.181,
            0.171,
            0.175,
            0.152,
            0.155,
            0.17,
            0.176,
            0.19,
            0.189,
            0.2
        ],
        [
            0.215,
            0.185,
            0.177,
            0.175,
            0.173,
            0.156,
            0.157,
            0.178,
            0.184,
            0.187,
            0.19,
            0.198
        ],
        [
            0.179,
            0.185,
            0.179,
            0.168,
            0.176,
            0.161,
            0.163,
            0.183,
            0.179,
            0.183,
            0.195,
            0.199
        ],
        [
            0.184,
            0.186,
            0.181,
            0.165,
            0.177,
            0.169,
            0.171,
            0.182,
            0.185,
            0.19,
            0.194,
            0.198
        ],
        [
            0.188,
            0.187,
            0.175,
            0.171,
            0.182,
            0.173,
            0.176,
            0.185,
            0.184,
            0.184,
            0.198,
            0.202
        ],
        [
            0.193,
            0.189,
            0.178,
            0.175,
            0.184,
            0.18,
            0.185,
            0.185,
            0.183,
            0.188,
            0.197,
            0.203
        ],
        [
            0.196,
            0.189,
            0.177,
            0.179,
            0.186,
            0.176,
            0.186,
            0.177,
            0.187,
            0.188,
            0.195,
            0.201
        ],
        [
            0.195,
            0.191,
            0.182,
            0.177,
            0.185,
            0.179,
            0.185,
            0.178,
            0.183,
            0.188,
            0.194,
            0.204
        ],
        [
            0.231,
            0.196,
            0.184,
            0.179,
            0.184,
            0.176,
            0.186,
            0.18,
            0.182,
            0.187,
            0.193,
            0.201
        ]
    ],
    "timestamp": "2026-04-10T19:57:48.346825",
    "label": "not_bee"
}